{
  "parent": "minecraft:recipes/root",
  "rewards": {
    "recipes": [
      "deepresonance:filter_material"
    ]
  },
  "criteria": {
    "has_coal": {
      "trigger": "minecraft:inventory_changed",
      "conditions": {
        "items": [
          {
            "tag": "minecraft:coals"
          }
        ]
      }
    },
    "has_sand": {
      "trigger": "minecraft:inventory_changed",
      "conditions": {
        "items": [
          {
            "tag": "minecraft:sand"
          }
        ]
      }
    },
    "has_gravel": {
      "trigger": "minecraft:inventory_changed",
      "conditions": {
        "items": [
          {
            "tag": "forge:gravel"
          }
        ]
      }
    },
    "has_the_recipe": {
      "trigger": "minecraft:recipe_unlocked",
      "conditions": {
        "recipe": "deepresonance:filter_material"
      }
    }
  },
  "requirements": [
    [
      "has_coal",
      "has_sand",
      "has_gravel",
      "has_the_recipe"
    ]
  ]
}