{
  "parent": "minecraft:block/cube",
  "elements": [
    {
      "faces": {
        "down": {
          "cullface": "down",
          "texture": "#down"
        },
        "east": {
          "cullface": "east",
          "texture": "#east"
        },
        "north": {
          "cullface": "north",
          "texture": "#north"
        },
        "south": {
          "cullface": "south",
          "texture": "#south"
        },
        "up": {
          "cullface": "up",
          "texture": "#up"
        },
        "west": {
          "cullface": "west",
          "texture": "#west"
        }
      },
      "from": [
        0,
        0,
        0
      ],
      "to": [
        16,
        16,
        16
      ]
    },
    {
      "faces": {
        "up": {
          "texture": "#up"
        }
      },
      "from": [
        0,
        0,
        0
      ],
      "to": [
        16,
        7,
        16
      ]
    },
    {
      "faces": {
        "down": {
          "cullface": "north",
          "texture": "#up"
        },
        "east": {
          "cullface": "north",
          "texture": "#up"
        },
        "north": {
          "cullface": "north",
          "texture": "#up"
        },
        "south": {
          "cullface": "north",
          "texture": "#up"
        },
        "up": {
          "cullface": "north",
          "texture": "#up"
        },
        "west": {
          "cullface": "north",
          "texture": "#up"
        }
      },
      "from": [
        16,
        16,
        16
      ],
      "to": [
        0,
        0,
        0
      ]
    }
  ],
  "render_type": "minecraft:translucent",
  "textures": {
    "down": "deepresonance:block/machine_bottom",
    "east": "deepresonance:block/machine_side",
    "north": "deepresonance:block/crystallizer",
    "particle": "deepresonance:block/crystallizer",
    "south": "deepresonance:block/machine_side",
    "up": "deepresonance:block/machine_top",
    "west": "deepresonance:block/machine_side"
  }
}